kalphacv/__init__.py
kalphacv/calculate_iaa.py
kalphacv/csv_data.py
kalphacv/hungarian_matching.py
kalphacv/iou.py
kalphacv/krippendorff_alpha.py
kalphacv/pre_processing.py
kalphacv/reliability_data.py
kalphacv-1.5.2.dist-info/LICENSE.txt
kalphacv-1.5.2.dist-info/METADATA
kalphacv-1.5.2.dist-info/WHEEL
kalphacv-1.5.2.dist-info/top_level.txt
kalphacv-1.5.2.dist-info/RECORD
