Metadata-Version: 2.1
Name: kalphacv
Version: 1.5.2
Summary: Package to calculate inter annotator agreement based on krippendorff's alpha for computer vision tasks
Author-email: David Tschirschwitz <david.tschirschwitz@uni-weimar.de>
Project-URL: Github, https://github.com/Madave94/kalphacv
Classifier: Programming Language :: Python :: 3
Classifier: License :: OSI Approved :: MIT License
Classifier: Operating System :: OS Independent
Requires-Python: >=3.8
License-File: LICENSE.txt
Requires-Dist: numpy
Requires-Dist: scipy
Requires-Dist: krippendorff
Requires-Dist: tqdm
Requires-Dist: shapely
